benchmarking.py
categories.py
constants.py
control.py
exceptions.py
knowledge_base.py
language_graphs.py
parser.py
parsetrees.py
rules.py
scoring.py
semantic_nets.py
tokens.py
utility.py
words.py
__init__.py
pyramids/benchmarking.py
pyramids/categorization.py
pyramids/control.py
pyramids/exceptions.py
pyramids/graphs.py
pyramids/parserules.py
pyramids/parsetrees.py
pyramids/parsing.py
pyramids/scoring.py
pyramids/tokenization.py
pyramids/utility.py
pyramids/__init__.py
pyramids/data/benchmarks.txt
pyramids/data/conjunctions.txt
pyramids/data/grammar.txt
pyramids/data/property_inheritance.txt
pyramids/data/pyramids.ini
pyramids/data/scores.txt
pyramids/data/special_words.txt
pyramids/data/suffixes.txt
pyramids-0.0.1.dist-info/DESCRIPTION.rst
pyramids-0.0.1.dist-info/METADATA
pyramids-0.0.1.dist-info/metadata.json
pyramids-0.0.1.dist-info/RECORD
pyramids-0.0.1.dist-info/top_level.txt
pyramids-0.0.1.dist-info/WHEEL
