Metadata-Version: 2.0
Name: pyramids
Version: 0.0.1
Summary: Pyramids Parser: English Language Semantic Extraction
Home-page: https://github.com/hosford42/pyramids
Author: Aaron Hosford
Author-email: hosford42@gmail.com
License: MIT
Requires-Dist: pyramids-categories (>=1.0)
